data/KD_default.json
data/WLH_mean.json
data/mass_1.mas20.txt
nuclear_rose-1.1.7.dist-info/licenses/LICENSE
rose/__init__.py
rose/__version__.py
rose/basis.py
rose/constants.py
rose/energized_interaction_eim.py
rose/free_solutions.py
rose/interaction.py
rose/interaction_eim.py
rose/koning_delaroche.py
rose/lagrangelegendersolver.py
rose/metrics.py
rose/mn_potential.py
rose/numerov_se.py
rose/reduced_basis_emulator.py
rose/scattering_amplitude_emulator.py
rose/schroedinger.py
rose/spin_orbit.py
rose/training.py
rose/utility.py
rose/wlh.py
nuclear_rose-1.1.7.dist-info/METADATA
nuclear_rose-1.1.7.dist-info/WHEEL
nuclear_rose-1.1.7.dist-info/top_level.txt
nuclear_rose-1.1.7.dist-info/RECORD
