Metadata-Version: 2.4
Name: nuclear-rose
Version: 1.1.7
Summary: The Reduced-Order Scattering Emulator (rose) is a user-friendly software for building efficient surrogate models for nuclear scattering.
Author: Daniel Odell, Pablo Giuliani, Kyle Godbey, Kyle Beyer, Moses Y.-H. Chan
License:                     GNU GENERAL PUBLIC LICENSE
Classifier: Programming Language :: Python :: 3
Classifier: License :: OSI Approved :: GNU General Public License v3 (GPLv3)
Classifier: Operating System :: OS Independent
Requires-Python: >=3.10
License-File: LICENSE
Requires-Dist: numba>=0.5
Requires-Dist: pandas>=2.0
Requires-Dist: seaborn>=0.10
Requires-Dist: numpy>=1.21.5
Requires-Dist: scipy>=1.10.1
Requires-Dist: mpmath>=1.2.1
Requires-Dist: tqdm>=4.62.3
Requires-Dist: jitr>=2.1.1
Requires-Dist: mkdocstrings>=0.22.0
Requires-Dist: mkdocstrings-python>=1.1.2
Requires-Dist: mkdocs-material>=9.1.18
Requires-Dist: mkdocs-jupyter>=0.24.2
Dynamic: license-file
